{
  "nodejs_url": "http://nodejs.org/",
  "npm_url": "https://www.npmjs.com/",
  "nvm_url": "https://github.com/creationix/nvm",
  "bitdeli_url": "https://bitdeli.com/free",
  "my_bitdeli_badge_url": "https://d2weczhvl823v0.cloudfront.net/okunishinishi/node-fur/trend.png",
  "my_repo_url": "https://github.com/okunishinishi/node-fur",
  "my_travis_url": "http://travis-ci.org/okunishinishi/node-fur",
  "my_travis_badge_url": "http://img.shields.io/travis/okunishinishi/node-fur.svg?style=flat",
  "my_license_url": "https://github.com/okunishinishi/node-fur/blob/master/LICENSE",
  "my_codeclimate_url": "http://codeclimate.com/github/okunishinishi/node-fur",
  "my_codeclimate_badge_url": "http://img.shields.io/codeclimate/github/okunishinishi/node-fur.svg?style=flat",
  "my_codeclimate_coverage_badge_url": "http://img.shields.io/codeclimate/coverage/github/okunishinishi/node-fur.svg?style=flat",
  "my_apiguide_url": "http://okunishinishi.github.io/node-fur/apiguide/module-fur.html",
  "my_coverage_url": "http://okunishinishi.github.io/node-fur/coverage/lcov-report",
  "my_coverage_report_url": "http://okunishinishi.github.io/node-fur/coverage/lcov-report/",
  "my_gratipay_url": "https://gratipay.com/okunishinishi/",
  "my_gratipay_budge_url": "http://img.shields.io/gratipay/okunishinishi.svg?style=flat",
  "my_npm_url": "http://www.npmjs.org/package/fur",
  "my_npm_budge_url": "http://img.shields.io/npm/v/fur.svg?style=flat",
  "my_tag_url": "http://github.com/okunishinishi/node-fur/releases/tag/",
  "my_tag_badge_url": "http://img.shields.io/github/tag/okunishinishi/node-fur.svg?style=flat",
  "my_gemnasium_url": "http://gemnasium.com/okunishinishi/node-fur",
  "my_gemnasium_badge_url": "http://img.shields.io/gemnasium/okunishinishi/node-fur.svg?style=flat",
  "my_inch_badge_url": "http://inch-ci.org/github/okunishinishi/node-fur.svg?branch=master",
  "my_inch_url": "http://inch-ci.org/github/okunishinishi/node-fur"
}
